rotel/__init__.py
rotel/agent.py
rotel/client.py
rotel/config.py
rotel/rotel-agent
sf_pyrotel-0.0.6.dist-info/LICENSE
sf_pyrotel-0.0.6.dist-info/METADATA
sf_pyrotel-0.0.6.dist-info/WHEEL
sf_pyrotel-0.0.6.dist-info/top_level.txt
sf_pyrotel-0.0.6.dist-info/RECORD
