Metadata-Version: 2.2
Name: sf-pyrotel
Version: 0.0.6
Summary: Rust OpenTelemetry collector
Home-page: https://github.com/streamfold/pyrotel
Author: Streamfold
Author-email: ray@streamfold.com
License: Apache License 2.0
Classifier: License :: OSI Approved :: Apache Software License
Classifier: Programming Language :: Python :: 3.10
Requires-Python: >=3.8
License-File: LICENSE
Dynamic: author
Dynamic: author-email
Dynamic: classifier
Dynamic: description
Dynamic: description-content-type
Dynamic: home-page
Dynamic: license
Dynamic: provides-extra
Dynamic: requires-python
Dynamic: summary
Provides-Extra: dev
Requires-Dist: pytest >=7.0 ; extra == 'dev'
Requires-Dist: twine >=6.1.0 ; extra == 'dev'
Requires-Dist: pkginfo >=1.12.0 ; extra == 'dev'
